{
  "df": "df-165",
  "ts": "2026-06-09T20:26:33.145843+00:00",
  "crux": "[CRUX-MK]",
  "winner_provider": "codex",
  "winner_tests_passed": true,
  "incumbent_q": 1.0,
  "winner_q": 1470.0,
  "improved": true,
  "variants": [
    {
      "provider": "incumbent",
      "parse_ok": true,
      "tests_passed": false,
      "n_tests": 3,
      "n_assert": 10,
      "coverage_pct": null,
      "q": 1.0,
      "error": null
    },
    {
      "provider": "codex",
      "parse_ok": true,
      "tests_passed": true,
      "n_tests": 2,
      "n_assert": 4,
      "coverage_pct": 92.0,
      "q": 1470.0,
      "error": null
    },
    {
      "provider": "sonnet",
      "parse_ok": false,
      "tests_passed": false,
      "n_tests": 0,
      "n_assert": null,
      "coverage_pct": null,
      "q": 0.0,
      "error": "kein 2-Block-Output (nach Retry)"
    }
  ],
  "canonical_verify": {
    "parse_ok": true,
    "tests_passed": true
  }
}